fastapi_users_db_ormar/__init__.py
fastapi_users_db_ormar/py.typed
fastapi_users_db_ormar-1.0.0.dist-info/LICENSE
fastapi_users_db_ormar-1.0.0.dist-info/WHEEL
fastapi_users_db_ormar-1.0.0.dist-info/METADATA
fastapi_users_db_ormar-1.0.0.dist-info/RECORD
