Metadata-Version: 2.1
Name: fastapi-users-db-ormar
Version: 1.0.0
Summary: FastAPI Users database adapter for ormar.
Home-page: https://github.com/fastapi-users/fastapi-users-db-ormar
Author: François Voron
Author-email: fvoron@gmail.com
Requires-Python: >=3.7
Classifier: License :: OSI Approved :: MIT License
Classifier: Development Status :: 5 - Production/Stable
Classifier: Framework :: AsyncIO
Classifier: Intended Audience :: Developers
Classifier: Programming Language :: Python :: 3.7
Classifier: Programming Language :: Python :: 3.8
Classifier: Programming Language :: Python :: 3.9
Classifier: Programming Language :: Python :: 3 :: Only
Classifier: Topic :: Internet :: WWW/HTTP :: Session
Requires-Dist: fastapi-users >= 6.1.2
Requires-Dist: ormar >=0.10.16,<0.11.0
Project-URL: Documentation, https://frankie567.github.io/fastapi-users
